{
  "isEditable": true,
  "data": {
    "sections": [
      {
        "id": "Section-1687297621026",
        "type": "Section",
        "group": "sections",
        "rows": ["Row-2347097621022"],
        "props": {
          "padding": "64px",
          "global": {
            "linkUrl": "",
            "linkTarget": "_self",
            "adminLabel": "Section"
          },
          "style": {
            "responsive": {
              "desktop": {
                "padding": {
                  "top": 54,
                  "bottom": 54,
                  "left": 0,
                  "right": 0
                }
              },
              "tablet": {
                "padding": {
                  "top": 50,
                  "bottom": 50,
                  "left": 0,
                  "right": 0
                }
              },
              "phone": {
                "padding": {
                  "top": 40,
                  "bottom": 40,
                  "left": 0,
                  "right": 0
                }
              }
            }
          }
        }
      }
    ],
    "rows": [
      {
        "id": "Row-2347097621022",
        "type": "Row",
        "group": "rows",
        "parent": {
          "id": "Section-1687297621026",
          "group": "sections" 
        },
        "columns": ["Column-113789456321", "Column-274000371976"],
        "props": {
          "padding": "64px"
        }
      }
    ],
    "columns": [
      {
        "id": "Column-113789456321",
        "type": "Column",
        "group": "columns",
        "parent": {
          "id": "Row-2347097621022",
          "group": "rows"
        },
        "modules": [],
        "columnType": "1_2",
        "props": {}
      },
      {
        "id": "Column-274000371976",
        "type": "Column",
        "group": "columns",
        "parent": {
          "id": "Row-2347097621022",
          "group": "rows"
        },
        "modules": [],
        "columnType": "1_2",
        "props": {}
      }
    ]
  }
}
